{
    "root": "",
    "title": "Java For Rookies",
    "gitbook": "3.2.2",
    "plugins": ["parts-autoindex", "exercises", "-highlight", "sunlight-highlighter", "html-minifier", "bring-yer-favicon"],
    "pluginsConfig": {
        "parts-autoindex": {
            "level": "1",
            "trim": "0"
        },
        "sunlight-highlighter": {
            "theme": "dark",
            "lineNumber": true
        },
        "favicons": {
            "favicon.ico": "assets/favicon.ico"
        }
    }
}